LICENSE
MANIFEST.in
README.rst
setup.py
dpmenu/__init__.py
dpmenu/apps.py
dpmenu/urls.py
dpmenu.egg-info/PKG-INFO
dpmenu.egg-info/SOURCES.txt
dpmenu.egg-info/dependency_links.txt
dpmenu.egg-info/requires.txt
dpmenu.egg-info/top_level.txt
dpmenu/admin/Menu.py
dpmenu/admin/__init__.py
dpmenu/managers/MenuManager.py
dpmenu/managers/__init__.py
dpmenu/migrations/0001_initial.py
dpmenu/migrations/0002_auto_20170524_2109.py
dpmenu/migrations/0003_abstractbasemenu_key.py
dpmenu/migrations/__init__.py
dpmenu/model_bases/AbstractBaseMenu.py
dpmenu/model_bases/__init__.py
dpmenu/models/Menu.py
dpmenu/models/__init__.py
dpmenu/serializers/__init__.py
dpmenu/serializers/menu_lc.py
dpmenu/serializers/menu_rud.py
dpmenu/signals/__init__.py
dpmenu/signals/handlers.py
dpmenu/views/__init__.py
dpmenu/views/menu_lc.py
dpmenu/views/menu_rud.py